resimpy/__init__.py
resimpy/grid.py
resimpy/schedule.py
resimpy-0.1.0.dist-info/LICENSE
resimpy-0.1.0.dist-info/WHEEL
resimpy-0.1.0.dist-info/METADATA
resimpy-0.1.0.dist-info/RECORD
